{
  "kind": "collectionType",
  "collectionName": "report_sessions",
  "info": {
    "singularName": "report-session",
    "pluralName": "report-sessions",
    "displayName": "Report Session",
    "description": ""
  },
  "options": {
    "draftAndPublish": false
  },
  "pluginOptions": {},
  "attributes": {
    "title": {
      "type": "string",
      "required": true,
      "maxLength": 255,
      "minLength": 1
    },
    "titleImage": {
      "allowedTypes": [
        "images",
        "files"
      ],
      "type": "media",
      "multiple": false,
      "required": true
    },
    "sessionImages": {
      "allowedTypes": [
        "images",
        "files"
      ],
      "type": "media",
      "multiple": true,
      "required": true
    }
  }
}
